MANIFEST.in
README.md
requirements.txt
setup.cfg
setup.py
choropie/ChoroPie.py
choropie/__init__.py
choropie/poly_functs.py
choropie.egg-info/PKG-INFO
choropie.egg-info/SOURCES.txt
choropie.egg-info/dependency_links.txt
choropie.egg-info/requires.txt
choropie.egg-info/top_level.txt
demo_projects/fatal_police_shootings/script.py
demo_projects/fatal_police_shootings/Data/PoliceKillingsUS.csv
demo_projects/fatal_police_shootings/Data/state_population_estimates.xlsx
demo_projects/fatal_police_shootings/Data/state_race.xlsx
demo_projects/fatal_police_shootings/Data/cb_2016_us_state_500k/cb_2016_us_state_500k.cpg
demo_projects/fatal_police_shootings/Data/cb_2016_us_state_500k/cb_2016_us_state_500k.dbf
demo_projects/fatal_police_shootings/Data/cb_2016_us_state_500k/cb_2016_us_state_500k.prj
demo_projects/fatal_police_shootings/Data/cb_2016_us_state_500k/cb_2016_us_state_500k.shp
demo_projects/fatal_police_shootings/Data/cb_2016_us_state_500k/cb_2016_us_state_500k.shp.ea.iso.xml
demo_projects/fatal_police_shootings/Data/cb_2016_us_state_500k/cb_2016_us_state_500k.shp.iso.xml
demo_projects/fatal_police_shootings/Data/cb_2016_us_state_500k/cb_2016_us_state_500k.shp.xml
demo_projects/fatal_police_shootings/Data/cb_2016_us_state_500k/cb_2016_us_state_500k.shx
demo_projects/fatal_police_shootings/Outputs/choro.png
demo_projects/fatal_police_shootings/Outputs/qwerty.png
demo_projects/fatal_police_shootings/Outputs/size_data.png
demo_projects/fatal_police_shootings/Outputs/size_ratios.png
demo_projects/us_election/script.py
demo_projects/us_election/Data/county_facts.csv
demo_projects/us_election/Data/county_facts_dictionary.csv
demo_projects/us_election/Data/database.sqlite
demo_projects/us_election/Data/hashes.txt
demo_projects/us_election/Data/primary_results.csv
demo_projects/us_election/Outputs/Pie_Plots/NYC_Sanders.png
demo_projects/us_election/Outputs/Pie_Plots/NYC_and_North_Sanders.png
demo_projects/us_election/Outputs/Pie_Plots/NYS_Clinton.png
demo_projects/us_election/Outputs/Pie_Plots/NYS_Sanders.png
demo_projects/us_election/Outputs/Pie_Plots/NYS_Trump.png
demo_projects/us_election/Outputs/Pie_Plots/NYS_and_North_Trump.png
