Metadata-Version: 1.1
Name: choropie
Version: 0.0.3
Summary: Create a choropleth map with pie charts in each polygon centroid.
Home-page: https://github.com/vinceniko/choropie
Author: Vincent Nikolayev
Author-email: vincent.nikolayev@gmail.com
License: BSD
Download-URL: https://github.com/vinceniko/choropie/tarball/0.0.3
Platform: UNKNOWN
Classifier: Development Status :: 3 - Alpha
Classifier: Intended Audience :: Developers
Classifier: Programming Language :: Python :: 3
